<?xml version="1.0" encoding="utf-8" ?>
<items pageNums="1" itemsNums="89" nowDate="2023-09-14 09:42:41" >
<item
					author="fei1019" 
					authorUid="9" 
					clickto="itemId-89" 
					authorHead="../uc.shenei.net/avatar.php@type=real&uid=9&size=small" 
					itemId="89" 
					dateline="2012-03-17" 
					digg="0" 
					reply="0" 
					copy="复制链接" 
					view="查看" 
					deleted="删除" 
					>%E5%85%AC%E8%80%83%E8%BF%87%E5%85%B3%E3%80%82%E3%80%82%E9%A1%BA%E5%88%A9%E6%AF%95%E4%B8%9A%7E%E6%96%B0%E5%BC%80%E5%A7%8B</item>
<item
					author="564864chen" 
					authorUid="564" 
					clickto="itemId-88" 
					authorHead="../uc.shenei.net/avatar.php@type=real&uid=564&size=small" 
					itemId="88" 
					dateline="2011-04-19" 
					digg="1" 
					reply="0" 
					copy="复制链接" 
					view="查看" 
					deleted="删除" 
					>%E6%84%BF%E8%87%AA%E5%B7%B1%E9%9D%A2%E6%9C%9D%E5%A4%A7%E6%B5%B7%EF%BC%8C%E6%98%A5%E6%9A%96%E8%8A%B1%E5%BC%80%E3%80%82%E8%87%AA%E5%B7%B1%E5%BE%88%E5%B9%B8%E7%A6%8F%E3%80%82</item>
<item
					author="01" 
					authorUid="1" 
					clickto="itemId-87" 
					authorHead="../uc.shenei.net/avatar.php@type=real&uid=1&size=small" 
					itemId="87" 
					dateline="2011-04-16" 
					digg="0" 
					reply="0" 
					copy="复制链接" 
					view="查看" 
					deleted="删除" 
					>%E6%88%91%E4%BB%AC%E5%AE%BF%E8%88%8D%E7%83%AD%E6%B0%B4%E5%99%A8%E5%BF%AB%E7%82%B9%E4%BF%AE%E5%A5%BD%E5%B0%B1%E5%A5%BD-%20%3D</item>
<item
					author="01" 
					authorUid="1" 
					clickto="itemId-86" 
					authorHead="../uc.shenei.net/avatar.php@type=real&uid=1&size=small" 
					itemId="86" 
					dateline="2011-01-01" 
					digg="0" 
					reply="0" 
					copy="复制链接" 
					view="查看" 
					deleted="删除" 
					>%E6%96%B0%E5%B9%B4%E5%BF%AB%E4%B9%90%EF%BD%9E</item>
<item
					author="fei1019" 
					authorUid="9" 
					clickto="itemId-85" 
					authorHead="../uc.shenei.net/avatar.php@type=real&uid=9&size=small" 
					itemId="85" 
					dateline="2010-12-23" 
					digg="0" 
					reply="3" 
					copy="复制链接" 
					view="查看" 
					deleted="删除" 
					>%E6%98%AF%E4%B8%8D%E6%98%AF%E5%B9%B3%E6%97%B6%E5%A4%AA%E5%9D%9A%E5%BC%BA%EF%BC%8C%E5%81%B6%E5%B0%94%E8%84%86%E5%BC%B1%E5%88%B0%E6%83%B3%E6%89%BE%E4%B8%AA%E5%9C%B0%E6%96%B9%E8%BA%B2%E8%B5%B7%E6%9D%A5%E5%93%AD%E9%83%BD%E6%89%BE%E4%B8%8D%E5%88%B0%EF%BC%9F</item>
<item
					author="%E5%86%B0%E5%B7%9D" 
					authorUid="1094" 
					clickto="itemId-84" 
					authorHead="../uc.shenei.net/avatar.php@type=real&uid=1094&size=small" 
					itemId="84" 
					dateline="2010-11-15" 
					digg="0" 
					reply="1" 
					copy="复制链接" 
					view="查看" 
					deleted="删除" 
					>%E6%9C%89%E7%82%B9%E5%A4%B1%E6%9C%9B%20%E6%9C%89%E7%82%B9%E6%97%A0%E5%A5%88%20%E4%B8%8D%E7%AE%A1%E6%80%8E%E6%A0%B7%20%E6%88%91%E4%B8%8D%E5%A6%A5%E5%8D%8F</item>
<item
					author="fei1019" 
					authorUid="9" 
					clickto="itemId-83" 
					authorHead="../uc.shenei.net/avatar.php@type=real&uid=9&size=small" 
					itemId="83" 
					dateline="2010-09-30" 
					digg="0" 
					reply="2" 
					copy="复制链接" 
					view="查看" 
					deleted="删除" 
					>%E5%86%AC%E5%A4%A9%E5%BF%AB%E7%82%B9%E6%9D%A5%7E%7E%7E%7E%E6%8A%8A%E8%87%AA%E5%B7%B1%E8%A3%B9%E8%B5%B7%E6%9D%A5%E6%AF%94%E8%BE%83%E6%9C%89%E5%AE%89%E5%85%A8%E6%84%9F%7E%7E</item>
<item
					author="hongling" 
					authorUid="144" 
					clickto="itemId-82" 
					authorHead="../uc.shenei.net/avatar.php@type=real&uid=144&size=small" 
					itemId="82" 
					dateline="2010-09-22" 
					digg="0" 
					reply="2" 
					copy="复制链接" 
					view="查看" 
					deleted="删除" 
					>%E8%BD%BB%E6%9D%BE%E8%BF%87%E5%AE%8C%E4%B8%89%E5%B9%B4%EF%BC%8C%E6%9C%80%E5%A5%BD%E4%B9%9F%E4%B8%8D%E8%A6%81%E6%8C%82%E7%A7%91</item>
<item
					author="freesix2007" 
					authorUid="258" 
					clickto="itemId-81" 
					authorHead="../uc.shenei.net/avatar.php@type=real&uid=258&size=small" 
					itemId="81" 
					dateline="2010-09-21" 
					digg="0" 
					reply="0" 
					copy="复制链接" 
					view="查看" 
					deleted="删除" 
					>%E5%B8%8C%E6%9C%9B%E8%87%AA%E5%B7%B1%E8%83%BD%E8%B5%B0%E7%9A%84%E6%9B%B4%E8%BF%9C%EF%BC%8C%E5%9D%9A%E6%8C%81%E4%B8%8B%E5%8E%BB%7E</item>
<item
					author="e5201" 
					authorUid="111" 
					clickto="itemId-80" 
					authorHead="../uc.shenei.net/avatar.php@type=real&uid=111&size=small" 
					itemId="80" 
					dateline="2010-09-19" 
					digg="0" 
					reply="0" 
					copy="复制链接" 
					view="查看" 
					deleted="删除" 
					>%E8%BF%B7%E8%8C%AB%E4%BA%86%E3%80%82%E3%80%82%E3%80%82</item>
<item
					author="01" 
					authorUid="1" 
					clickto="itemId-79" 
					authorHead="../uc.shenei.net/avatar.php@type=real&uid=1&size=small" 
					itemId="79" 
					dateline="2010-09-19" 
					digg="0" 
					reply="0" 
					copy="复制链接" 
					view="查看" 
					deleted="删除" 
					>%E6%88%91%E5%88%B0%E5%BA%95%E6%9C%89%E6%B2%A1%E6%9C%89%E5%A5%B3%E6%9C%8B%E5%8F%8B%E5%91%A2%EF%BC%9F%0D%E7%BB%8F%E5%B8%B8%E8%BF%99%E6%A0%B7%E9%97%AE%E8%87%AA%E5%B7%B1%E5%95%8A%E3%80%82%E3%80%82%E3%80%82</item>
<item
					author="ybxstc" 
					authorUid="23" 
					clickto="itemId-78" 
					authorHead="../uc.shenei.net/avatar.php@type=real&uid=23&size=small" 
					itemId="78" 
					dateline="2010-09-17" 
					digg="0" 
					reply="0" 
					copy="复制链接" 
					view="查看" 
					deleted="删除" 
					>kaixuele%20%20%20hao%20jiahuo</item>
<item
					author="hongling" 
					authorUid="144" 
					clickto="itemId-77" 
					authorHead="../uc.shenei.net/avatar.php@type=real&uid=144&size=small" 
					itemId="77" 
					dateline="2010-08-28" 
					digg="0" 
					reply="0" 
					copy="复制链接" 
					view="查看" 
					deleted="删除" 
					>%E6%AD%A6%E8%89%BA%EF%BC%8C%E5%8A%A0%E6%B2%B9%EF%BC%8C%E4%B8%80%E5%AE%9A%E8%A6%81%E6%8B%BF%E5%86%A0%E5%86%9B%0D</item>
<item
					author="564864chen" 
					authorUid="564" 
					clickto="itemId-76" 
					authorHead="../uc.shenei.net/avatar.php@type=real&uid=564&size=small" 
					itemId="76" 
					dateline="2010-07-28" 
					digg="0" 
					reply="0" 
					copy="复制链接" 
					view="查看" 
					deleted="删除" 
					>%E5%92%8C%E7%BE%8E%E8%BE%B0%E6%B0%B8%E8%BF%9C%E5%9C%A8%E4%B8%80%E8%B5%B7%7E%7E%E5%98%BB%E5%98%BB</item>
<item
					author="hongling" 
					authorUid="144" 
					clickto="itemId-75" 
					authorHead="../uc.shenei.net/avatar.php@type=real&uid=144&size=small" 
					itemId="75" 
					dateline="2010-07-19" 
					digg="0" 
					reply="1" 
					copy="复制链接" 
					view="查看" 
					deleted="删除" 
					>%E6%99%9A%E5%AE%89%EF%BC%8C%E5%A4%A7%E5%AE%B6</item>
<item
					author="hongling" 
					authorUid="144" 
					clickto="itemId-74" 
					authorHead="../uc.shenei.net/avatar.php@type=real&uid=144&size=small" 
					itemId="74" 
					dateline="2010-07-19" 
					digg="0" 
					reply="0" 
					copy="复制链接" 
					view="查看" 
					deleted="删除" 
					>%E6%96%87%EF%BC%8C%E4%BD%A0%E8%BF%87%E5%BE%97%E5%A5%BD%E5%90%97%EF%BC%8C%E5%AF%B9%E4%B8%8D%E8%B5%B7</item>
<item
					author="01" 
					authorUid="1" 
					clickto="itemId-73" 
					authorHead="../uc.shenei.net/avatar.php@type=real&uid=1&size=small" 
					itemId="73" 
					dateline="2010-06-30" 
					digg="0" 
					reply="0" 
					copy="复制链接" 
					view="查看" 
					deleted="删除" 
					>%E4%B8%8B%E5%8D%88%E8%80%83%E8%AF%95%E8%A6%81%E8%BF%87%E5%95%8A%E5%95%8A%7E%7E%7E</item>
<item
					author="Sweet" 
					authorUid="2" 
					clickto="itemId-72" 
					authorHead="../uc.shenei.net/avatar.php@type=real&uid=2&size=small" 
					itemId="72" 
					dateline="2010-06-28" 
					digg="0" 
					reply="4" 
					copy="复制链接" 
					view="查看" 
					deleted="删除" 
					>%E6%88%91%E6%83%B3%E5%9B%9E%E5%AE%B6%7E%2A%2A%2A%2A%2A%2A</item>
<item
					author="01" 
					authorUid="1" 
					clickto="itemId-71" 
					authorHead="../uc.shenei.net/avatar.php@type=real&uid=1&size=small" 
					itemId="71" 
					dateline="2010-06-26" 
					digg="0" 
					reply="1" 
					copy="复制链接" 
					view="查看" 
					deleted="删除" 
					>%E6%9C%89%E4%B8%80%E7%A7%8D%E6%84%9F%E8%A7%89%E3%80%82%E3%80%82%E6%88%91%E8%BF%98%E6%98%AF%E4%B8%80%E4%B8%AA%E4%BA%BA%E3%80%82%E3%80%82%E3%80%82</item>
<item
					author="e5201" 
					authorUid="111" 
					clickto="itemId-70" 
					authorHead="../uc.shenei.net/avatar.php@type=real&uid=111&size=small" 
					itemId="70" 
					dateline="2010-06-26" 
					digg="0" 
					reply="0" 
					copy="复制链接" 
					view="查看" 
					deleted="删除" 
					>%E5%A5%BD%E5%BF%83%E6%83%85%7E%E5%BE%88%E5%A4%9A%E5%8A%9F%E8%83%BD%E9%83%BD%E5%9B%9E%E6%9D%A5%E4%BA%86%E3%80%82%E3%80%82%E3%80%82</item>
<item
					author="freesix2007" 
					authorUid="258" 
					clickto="itemId-69" 
					authorHead="../uc.shenei.net/avatar.php@type=real&uid=258&size=small" 
					itemId="69" 
					dateline="2010-06-24" 
					digg="1" 
					reply="0" 
					copy="复制链接" 
					view="查看" 
					deleted="删除" 
					>%E5%AE%9D%E8%B4%9D%E8%80%81%E5%A9%86%20%E8%80%81%E5%85%AC%E7%88%B1%E4%BD%A0%EF%BC%81%E5%93%88%E5%93%88%EF%BC%81</item>
<item
					author="Sweet" 
					authorUid="2" 
					clickto="itemId-68" 
					authorHead="../uc.shenei.net/avatar.php@type=real&uid=2&size=small" 
					itemId="68" 
					dateline="2010-06-18" 
					digg="0" 
					reply="1" 
					copy="复制链接" 
					view="查看" 
					deleted="删除" 
					>%E7%82%8E%E4%BA%9A%E7%BA%B6%7E%7E%E4%BF%9D%E4%BD%91%E6%88%91%E6%98%8E%E5%A4%A94%E7%BA%A7%E9%80%9A%E8%BF%87%E5%93%A6%7E%E5%93%88%E5%93%88</item>
<item
					author="chenwu27" 
					authorUid="33" 
					clickto="itemId-67" 
					authorHead="../uc.shenei.net/avatar.php@type=real&uid=33&size=small" 
					itemId="67" 
					dateline="2010-06-18" 
					digg="0" 
					reply="0" 
					copy="复制链接" 
					view="查看" 
					deleted="删除" 
					>%E5%8A%A0%E6%B2%B9%EF%BD%9E%EF%BD%9E%EF%BC%81</item>
<item
					author="Sweet" 
					authorUid="2" 
					clickto="itemId-66" 
					authorHead="../uc.shenei.net/avatar.php@type=real&uid=2&size=small" 
					itemId="66" 
					dateline="2010-05-10" 
					digg="0" 
					reply="1" 
					copy="复制链接" 
					view="查看" 
					deleted="删除" 
					>%E5%BF%99%E5%AE%8C%E8%A6%81%E5%A5%BD%E5%A5%BD%E4%BC%91%E6%81%AF%EF%BC%8C%E4%B8%8D%E8%A6%81%E5%A4%AA%E7%B4%AF%E4%BA%86%E5%93%88%7E%7E%E4%BC%9A%E5%BF%83%E7%96%BC...</item>
<item
					author="cjr0304" 
					authorUid="113" 
					clickto="itemId-65" 
					authorHead="../uc.shenei.net/avatar.php@type=real&uid=113&size=small" 
					itemId="65" 
					dateline="2010-05-02" 
					digg="0" 
					reply="0" 
					copy="复制链接" 
					view="查看" 
					deleted="删除" 
					>%E5%91%83%EF%BC%8C%E6%97%A0%E8%81%8A%E7%9A%84%E7%94%9F%E6%B4%BB%EF%BC%8C</item>
<item
					author="cjr0304" 
					authorUid="113" 
					clickto="itemId-64" 
					authorHead="../uc.shenei.net/avatar.php@type=real&uid=113&size=small" 
					itemId="64" 
					dateline="2010-05-01" 
					digg="0" 
					reply="2" 
					copy="复制链接" 
					view="查看" 
					deleted="删除" 
					>%E5%A4%A9%E5%95%A6%20%E8%AE%A9%E6%88%91%E6%8D%A1%E9%92%B1%E5%90%A7</item>
<item
					author="xi77" 
					authorUid="4" 
					clickto="itemId-63" 
					authorHead="../uc.shenei.net/avatar.php@type=real&uid=4&size=small" 
					itemId="63" 
					dateline="2010-04-26" 
					digg="0" 
					reply="5" 
					copy="复制链接" 
					view="查看" 
					deleted="删除" 
					>%E6%88%91%E5%B8%8C%E6%9C%9B%E5%9C%A8%E4%BD%A0%E7%9C%BC%E9%87%8C%E6%88%91%E8%BF%98%E6%98%AF%E5%8E%9F%E6%9D%A5%E7%9A%84%E6%A0%B7%E5%AD%90%E3%80%82</item>
<item
					author="lemeimei" 
					authorUid="211" 
					clickto="itemId-62" 
					authorHead="../uc.shenei.net/avatar.php@type=real&uid=211&size=small" 
					itemId="62" 
					dateline="2010-04-22" 
					digg="0" 
					reply="0" 
					copy="复制链接" 
					view="查看" 
					deleted="删除" 
					>%E6%88%91%E7%9A%84%E4%B9%A6%E5%BF%AB%E7%82%B9%E5%87%BA%E6%9D%A5%E5%91%80%EF%BC%8C%E8%BF%99%E6%A0%B7%E5%B0%B1%E5%8F%AF%E4%BB%A5%E5%90%83%E8%B1%86%E8%85%90%E7%89%87%21</item>
<item
					author="xi77" 
					authorUid="4" 
					clickto="itemId-61" 
					authorHead="../uc.shenei.net/avatar.php@type=real&uid=4&size=small" 
					itemId="61" 
					dateline="2010-04-22" 
					digg="0" 
					reply="1" 
					copy="复制链接" 
					view="查看" 
					deleted="删除" 
					>%E6%98%AF%E8%B0%81%E8%AF%B4%E7%9A%84%E6%84%BF%E6%9C%9B%E8%A6%81%E5%A4%A7%E5%A3%B0%E8%AF%B4%E5%86%99%E5%87%BA%E6%9D%A5%E6%89%8D%E6%9C%89%E4%BA%BA%E6%9B%BF%E6%88%91%E5%AE%9E%E7%8E%B0%E3%80%82</item>
<item
					author="xi77" 
					authorUid="4" 
					clickto="itemId-60" 
					authorHead="../uc.shenei.net/avatar.php@type=real&uid=4&size=small" 
					itemId="60" 
					dateline="2010-04-22" 
					digg="0" 
					reply="0" 
					copy="复制链接" 
					view="查看" 
					deleted="删除" 
					>%E6%88%91%E4%BB%AC%E5%AE%B6%E6%9E%9C%E5%84%BF%E8%A6%81%E5%92%8C%E5%B0%8F%E6%B7%A6%E6%B7%A6%E6%9C%89%E5%BE%88%E5%A4%A7%E5%BE%88%E5%A4%A7%E7%9A%84%E5%B9%B8%E7%A6%8F%E5%93%A6%E3%80%82</item>
<item
					author="Sweet" 
					authorUid="2" 
					clickto="itemId-59" 
					authorHead="../uc.shenei.net/avatar.php@type=real&uid=2&size=small" 
					itemId="59" 
					dateline="2010-04-22" 
					digg="0" 
					reply="3" 
					copy="复制链接" 
					view="查看" 
					deleted="删除" 
					>%E6%98%8E%E5%A4%A98%E8%A6%81%E4%B8%8B%E9%9B%A8..</item>
<item
					author="xi77" 
					authorUid="4" 
					clickto="itemId-58" 
					authorHead="../uc.shenei.net/avatar.php@type=real&uid=4&size=small" 
					itemId="58" 
					dateline="2010-04-14" 
					digg="0" 
					reply="2" 
					copy="复制链接" 
					view="查看" 
					deleted="删除" 
					>%E6%9C%89%20%E8%B0%81%20%E8%A6%81%20%E7%BB%99%20%E6%88%91%20%E4%BA%A4%20%E4%B8%8B%20%E8%8A%B1%20%E8%B4%B9%20%E7%9A%84%20%E5%90%96%E3%80%82%E3%80%82%E3%80%82</item>
<item
					author="Sweet" 
					authorUid="2" 
					clickto="itemId-57" 
					authorHead="../uc.shenei.net/avatar.php@type=real&uid=2&size=small" 
					itemId="57" 
					dateline="2010-04-12" 
					digg="2" 
					reply="0" 
					copy="复制链接" 
					view="查看" 
					deleted="删除" 
					>%E6%88%91%E6%83%B3%E5%9C%A811%E7%82%B9%E5%8D%8A%E4%B9%8B%E5%89%8D%E7%9D%A1%E8%A7%89...</item>
<item
					author="xi77" 
					authorUid="4" 
					clickto="itemId-56" 
					authorHead="../uc.shenei.net/avatar.php@type=real&uid=4&size=small" 
					itemId="56" 
					dateline="2010-04-11" 
					digg="0" 
					reply="5" 
					copy="复制链接" 
					view="查看" 
					deleted="删除" 
					>%E6%98%8E%E5%A4%A9%E4%B8%8B%E9%9B%A8%E5%90%A7%E3%80%82%E3%80%82%E3%80%82%E3%80%82</item>
<item
					author="fei1019" 
					authorUid="9" 
					clickto="itemId-55" 
					authorHead="../uc.shenei.net/avatar.php@type=real&uid=9&size=small" 
					itemId="55" 
					dateline="2010-04-10" 
					digg="0" 
					reply="2" 
					copy="复制链接" 
					view="查看" 
					deleted="删除" 
					>%E6%AF%94%E8%B5%9B%E5%8A%A0%E6%B2%B9%EF%BC%81%E8%87%AA%E5%B7%B1%E7%9A%84%E4%BC%A4%E4%B9%9F%E5%B0%8F%E5%BF%83%E4%B8%80%E7%82%B9%EF%BC%81</item>
<item
					author="Sweet" 
					authorUid="2" 
					clickto="itemId-54" 
					authorHead="../uc.shenei.net/avatar.php@type=real&uid=2&size=small" 
					itemId="54" 
					dateline="2010-04-10" 
					digg="0" 
					reply="10" 
					copy="复制链接" 
					view="查看" 
					deleted="删除" 
					>%E6%99%9A%E4%B8%8A%E6%AF%94%E8%B5%9B%E5%8A%A0%E6%B2%B9%E5%93%88%20%20%E6%88%91%E7%9C%8B%E5%A5%BD%E4%BD%A0%E5%93%9F</item>
<item
					author="Sweet" 
					authorUid="2" 
					clickto="itemId-53" 
					authorHead="../uc.shenei.net/avatar.php@type=real&uid=2&size=small" 
					itemId="53" 
					dateline="2010-04-08" 
					digg="0" 
					reply="5" 
					copy="复制链接" 
					view="查看" 
					deleted="删除" 
					>%E4%B8%83%E9%87%8C%E9%A6%99%20..%E4%BD%A0%E8%A6%81%E9%96%8B%E8%8A%B1%E5%93%A6%7E%7E</item>
<item
					author="weibin" 
					authorUid="40" 
					clickto="itemId-52" 
					authorHead="../uc.shenei.net/avatar.php@type=real&uid=40&size=small" 
					itemId="52" 
					dateline="2010-03-24" 
					digg="0" 
					reply="0" 
					copy="复制链接" 
					view="查看" 
					deleted="删除" 
					>%E5%A5%BD%E5%A5%BD%E7%94%9F%E6%B4%BB%C2%B7%C2%B7%C2%B7</item>
<item
					author="ybxstc" 
					authorUid="23" 
					clickto="itemId-51" 
					authorHead="../uc.shenei.net/avatar.php@type=real&uid=23&size=small" 
					itemId="51" 
					dateline="2010-03-23" 
					digg="0" 
					reply="1" 
					copy="复制链接" 
					view="查看" 
					deleted="删除" 
					>%E5%B0%8F%20e%0D%E9%AA%97%E4%BA%BA%EF%BC%81%EF%BC%81%E6%88%91%E8%AE%B8%E6%84%BF%E4%B8%8D%E6%8C%82%E7%A7%91%EF%BC%81%EF%BC%81%EF%BC%81%E5%8F%AF%E6%98%AF%E5%81%8F%E5%81%8F%E6%8C%82%E4%BA%86%EF%BC%81%EF%BC%81%E4%BB%A5%E5%89%8D%E6%B2%A1%E8%AE%B8%E6%84%BF%E5%B0%B1%E6%B2%A1%E6%8C%82%EF%BC%81%EF%BC%81%EF%BC%81%E9%AA%97%E5%AD%90%E5%95%8A%E5%95%8A%E5%95%8A%E5%95%8A%E5%95%8A%E5%95%8A%E5%95%8A%EF%BC%81%EF%BC%81%EF%BC%81</item>
<item
					author="01" 
					authorUid="1" 
					clickto="itemId-50" 
					authorHead="../uc.shenei.net/avatar.php@type=real&uid=1&size=small" 
					itemId="50" 
					dateline="2010-03-15" 
					digg="0" 
					reply="0" 
					copy="复制链接" 
					view="查看" 
					deleted="删除" 
					>%E4%B8%8A%E5%AD%A6%E6%9C%9F%E6%88%91%E7%9A%84%E5%B0%8F%E7%A0%B4%E8%BD%A6%E6%94%BE%E5%B8%88%E5%A4%A7%E8%A2%AB%E5%81%B7%E4%BA%86%EF%BC%8C%E4%BF%9D%E4%BD%91%E8%BF%99%E5%AD%A6%E6%9C%9F%E6%88%91%E7%9A%84%E5%A4%A7%E7%BB%B5%E7%BE%8A%E8%A6%81%E5%A5%BD%E5%A5%BD%E7%9A%84%E5%95%8A%EF%BC%81%7E%7E</item>
<item
					author="weibin" 
					authorUid="40" 
					clickto="itemId-49" 
					authorHead="../uc.shenei.net/avatar.php@type=real&uid=40&size=small" 
					itemId="49" 
					dateline="2010-03-14" 
					digg="0" 
					reply="0" 
					copy="复制链接" 
					view="查看" 
					deleted="删除" 
					>%E9%82%A3%E4%B8%AA%E4%BA%BA%C2%B7%C2%B7%C2%B7%E4%BD%A0%E8%A6%81%E5%B9%B8%E7%A6%8F%EF%BC%81</item>
<item
					author="chenwu27" 
					authorUid="33" 
					clickto="itemId-48" 
					authorHead="../uc.shenei.net/avatar.php@type=real&uid=33&size=small" 
					itemId="48" 
					dateline="2010-03-10" 
					digg="0" 
					reply="0" 
					copy="复制链接" 
					view="查看" 
					deleted="删除" 
					>%E5%BF%83%E6%83%85%E7%9A%84%E5%A4%AA%E9%98%B3%E3%80%82%E3%80%82%E3%80%82%E3%80%82</item>
<item
					author="Sweet" 
					authorUid="2" 
					clickto="itemId-47" 
					authorHead="../uc.shenei.net/avatar.php@type=real&uid=2&size=small" 
					itemId="47" 
					dateline="2010-03-08" 
					digg="0" 
					reply="0" 
					copy="复制链接" 
					view="查看" 
					deleted="删除" 
					>%E5%AE%A0%E7%89%A9%E4%BD%A0%E8%A6%81%E5%BC%80%E5%BF%83..</item>
<item
					author="xi77" 
					authorUid="4" 
					clickto="itemId-46" 
					authorHead="../uc.shenei.net/avatar.php@type=real&uid=4&size=small" 
					itemId="46" 
					dateline="2010-03-05" 
					digg="0" 
					reply="0" 
					copy="复制链接" 
					view="查看" 
					deleted="删除" 
					>%E4%BA%B2%E7%88%B1%EF%BC%8C%E5%B8%8C%E6%9C%9B%E4%BD%A0%E8%83%BD%E5%9D%9A%E6%8C%81%E4%B8%8B%E5%8E%BB</item>
<item
					author="ybxstc" 
					authorUid="23" 
					clickto="itemId-45" 
					authorHead="../uc.shenei.net/avatar.php@type=real&uid=23&size=small" 
					itemId="45" 
					dateline="2010-03-01" 
					digg="0" 
					reply="1" 
					copy="复制链接" 
					view="查看" 
					deleted="删除" 
					>%E5%BC%80%E5%AD%A6%E5%95%A6%EF%BC%81%EF%BC%81%E5%A5%BD%E5%BC%80%E5%BF%83%E5%95%8A%E5%95%8A%E5%95%8A%E5%95%8A%E5%95%8A%E5%95%8A%E5%95%8A%20%20</item>
<item
					author="%E6%AE%8B%E9%A3%8E%E8%BF%BD%E6%9C%88" 
					authorUid="27" 
					clickto="itemId-44" 
					authorHead="../uc.shenei.net/avatar.php@type=real&uid=27&size=small" 
					itemId="44" 
					dateline="2010-02-25" 
					digg="0" 
					reply="0" 
					copy="复制链接" 
					view="查看" 
					deleted="删除" 
					>%E5%8F%88%E8%A6%81%E4%B8%8A%E5%AD%A6%E4%BA%86</item>
<item
					author="xi77" 
					authorUid="4" 
					clickto="itemId-43" 
					authorHead="../uc.shenei.net/avatar.php@type=real&uid=4&size=small" 
					itemId="43" 
					dateline="2010-02-10" 
					digg="0" 
					reply="0" 
					copy="复制链接" 
					view="查看" 
					deleted="删除" 
					>%E6%88%91%E7%9A%84%E6%9E%9C%E5%84%BF%E5%92%8C%E8%80%81%E5%85%AC%E6%B0%B8%E8%BF%9C%E5%B9%B8%E7%A6%8F</item>
<item
					author="%E5%B0%8F%E8%AF%BA" 
					authorUid="176" 
					clickto="itemId-42" 
					authorHead="../uc.shenei.net/avatar.php@type=real&uid=176&size=small" 
					itemId="42" 
					dateline="2010-02-10" 
					digg="0" 
					reply="0" 
					copy="复制链接" 
					view="查看" 
					deleted="删除" 
					>%E5%B8%8C%E6%9C%9B%E8%83%BD%E6%89%BE%E5%88%B0%E4%B8%80%E4%B8%AA%E5%A5%BD%E7%94%B7%E5%AD%A9%E5%84%BF%EF%BC%8C%E5%81%9A%E7%94%B7%E6%9C%8B%E5%8F%8B</item>
<item
					author="%E6%AE%8B%E9%A3%8E%E8%BF%BD%E6%9C%88" 
					authorUid="27" 
					clickto="itemId-41" 
					authorHead="../uc.shenei.net/avatar.php@type=real&uid=27&size=small" 
					itemId="41" 
					dateline="2010-02-07" 
					digg="0" 
					reply="1" 
					copy="复制链接" 
					view="查看" 
					deleted="删除" 
					>%E5%93%87%E5%93%87%EF%BC%8C%E4%BB%A5%E5%89%8D%E5%B1%85%E7%84%B6%E4%B8%8D%E7%9F%A5%E9%81%93%E8%83%8C%E6%99%AF%E5%8F%AF%E4%BB%A5%E8%B7%9F%E7%9D%80%E6%97%B6%E9%97%B4%E6%94%B9%E5%8F%98%E5%95%8A%EF%BC%81%EF%BC%81%EF%BC%81</item>
<item
					author="%E6%AE%8B%E9%A3%8E%E8%BF%BD%E6%9C%88" 
					authorUid="27" 
					clickto="itemId-40" 
					authorHead="../uc.shenei.net/avatar.php@type=real&uid=27&size=small" 
					itemId="40" 
					dateline="2010-02-01" 
					digg="0" 
					reply="2" 
					copy="复制链接" 
					view="查看" 
					deleted="删除" 
					>../speely.web-86.com/_25E5_2585_2588_25E7_2594_25A8_25E7_259D_2580_25E4_25BA_258C_25E7_25BA_25A7_25E5_259F_259F_25E5_2590_258D</item>
<item
					author="01" 
					authorUid="1" 
					clickto="itemId-39" 
					authorHead="../uc.shenei.net/avatar.php@type=real&uid=1&size=small" 
					itemId="39" 
					dateline="2010-01-28" 
					digg="0" 
					reply="0" 
					copy="复制链接" 
					view="查看" 
					deleted="删除" 
					>%E7%BB%88%E4%BA%8E%E5%85%A8%E8%80%83%E5%AE%8C%E4%BA%86%E3%80%82%E3%80%82%E8%80%83%E5%B7%AE%E4%BA%86%E4%B9%9F%E5%A5%BD%E5%BF%83%E6%83%85%E5%93%88%7E</item>
<item
					author="%E6%AE%8B%E9%A3%8E%E8%BF%BD%E6%9C%88" 
					authorUid="27" 
					clickto="itemId-38" 
					authorHead="../uc.shenei.net/avatar.php@type=real&uid=27&size=small" 
					itemId="38" 
					dateline="2010-01-28" 
					digg="0" 
					reply="1" 
					copy="复制链接" 
					view="查看" 
					deleted="删除" 
					>%E4%B8%8B%E5%8D%88%E5%B0%B1%E8%80%83%E4%BA%86%7E%7E</item>
<item
					author="%E6%AE%8B%E9%A3%8E%E8%BF%BD%E6%9C%88" 
					authorUid="27" 
					clickto="itemId-37" 
					authorHead="../uc.shenei.net/avatar.php@type=real&uid=27&size=small" 
					itemId="37" 
					dateline="2010-01-27" 
					digg="0" 
					reply="1" 
					copy="复制链接" 
					view="查看" 
					deleted="删除" 
					>%E5%9B%9B%E5%A4%A7%E5%90%8D%E8%A1%A5%E7%9A%84%E5%88%91%E6%B3%95%E8%80%81%E5%B8%88%7E%7E%7E%7E</item>
<item
					author="xi77" 
					authorUid="4" 
					clickto="itemId-36" 
					authorHead="../uc.shenei.net/avatar.php@type=real&uid=4&size=small" 
					itemId="36" 
					dateline="2010-01-26" 
					digg="0" 
					reply="1" 
					copy="复制链接" 
					view="查看" 
					deleted="删除" 
					>%E5%A4%9A%E5%B8%8C%E6%9C%9B%E4%BD%A0%E8%83%BD%E5%B8%AE%E6%88%91%EF%BC%8C72%E5%88%86%E9%92%9F%E7%9A%84%E5%BD%95%E9%9F%B3%E6%88%91%E7%9A%84%E5%90%AC%E5%88%86%E4%B8%8D%E6%B8%85%EF%BC%8C%E8%80%B3%E6%9C%B5%E7%9C%9F%E7%9A%84%E4%B8%8D%E8%A1%8C%E5%8F%BB%EF%BC%8C%E5%B0%B1%E7%AE%97%E7%86%AC%E5%A4%9C%E4%B9%9F%E8%A6%81%E6%89%93%E5%87%BA%E6%9D%A5%E3%80%82%E3%80%82%E5%8A%A0%E6%B2%B9%EF%BC%8C%E6%98%8E%E5%A4%A9%E8%83%BD%E6%8A%8A%E4%BD%9C%E4%B8%9A%E5%8F%AB%E5%87%BA%E6%9D%A5%EF%BC%81</item>
<item
					author="%E6%AE%8B%E9%A3%8E%E8%BF%BD%E6%9C%88" 
					authorUid="27" 
					clickto="itemId-35" 
					authorHead="../uc.shenei.net/avatar.php@type=real&uid=27&size=small" 
					itemId="35" 
					dateline="2010-01-26" 
					digg="0" 
					reply="0" 
					copy="复制链接" 
					view="查看" 
					deleted="删除" 
					>%E6%9C%80%E5%90%8E%E4%B8%A4%E7%A7%91%E4%BA%86</item>
<item
					author="ybxstc" 
					authorUid="23" 
					clickto="itemId-34" 
					authorHead="../uc.shenei.net/avatar.php@type=real&uid=23&size=small" 
					itemId="34" 
					dateline="2010-01-26" 
					digg="0" 
					reply="0" 
					copy="复制链接" 
					view="查看" 
					deleted="删除" 
					>%E5%BF%AB%E8%A6%81%E6%94%BE%E5%81%87%E5%92%AF%EF%BC%81%E5%93%88%E5%93%88%E5%95%8A%E5%93%88%E5%93%88%EF%BC%81%0D</item>
<item
					author="01" 
					authorUid="1" 
					clickto="itemId-33" 
					authorHead="../uc.shenei.net/avatar.php@type=real&uid=1&size=small" 
					itemId="33" 
					dateline="2010-01-26" 
					digg="0" 
					reply="0" 
					copy="复制链接" 
					view="查看" 
					deleted="删除" 
					>%E5%87%BA%E5%A4%AA%E9%98%B3%E4%BA%86%E5%93%9F%7E%0D%E7%9C%8B%E6%9D%A5%E6%98%A8%E5%A4%A9%E5%86%92%E7%9D%80%E4%B8%A5%E5%AF%92%E6%B4%97%E9%82%A3%E4%BB%B6%E6%9C%80%E5%8E%9A%E7%9A%84%E5%A4%96%E5%A5%97%E6%B2%A1%E4%BA%8F%E5%93%88%E5%93%88%EF%BC%81</item>
<item
					author="%E6%AE%8B%E9%A3%8E%E8%BF%BD%E6%9C%88" 
					authorUid="27" 
					clickto="itemId-32" 
					authorHead="../uc.shenei.net/avatar.php@type=real&uid=27&size=small" 
					itemId="32" 
					dateline="2010-01-25" 
					digg="0" 
					reply="0" 
					copy="复制链接" 
					view="查看" 
					deleted="删除" 
					>%E5%9B%9E%E5%AE%B6%7E%7E%7E</item>
<item
					author="01" 
					authorUid="1" 
					clickto="itemId-31" 
					authorHead="../uc.shenei.net/avatar.php@type=real&uid=1&size=small" 
					itemId="31" 
					dateline="2010-01-23" 
					digg="0" 
					reply="1" 
					copy="复制链接" 
					view="查看" 
					deleted="删除" 
					>%E4%BB%8A%E5%A4%A9%E5%A5%BD%E5%86%B7%E5%95%8A%7E%E4%BD%A0%E5%86%B7%E4%B8%8D%E5%86%B7%E5%91%A2%EF%BC%9F</item>
<item
					author="ybxstc" 
					authorUid="23" 
					clickto="itemId-30" 
					authorHead="../uc.shenei.net/avatar.php@type=real&uid=23&size=small" 
					itemId="30" 
					dateline="2010-01-20" 
					digg="0" 
					reply="1" 
					copy="复制链接" 
					view="查看" 
					deleted="删除" 
					>%E8%AE%A9%E6%98%A5%E5%93%A5%E4%BF%9D%E4%BD%91%E5%93%A5%E4%B8%8D%E6%8C%82%E7%A7%91%EF%BC%81%EF%BC%81%EF%BC%81</item>
<item
					author="xi77" 
					authorUid="4" 
					clickto="itemId-29" 
					authorHead="../uc.shenei.net/avatar.php@type=real&uid=4&size=small" 
					itemId="29" 
					dateline="2010-01-20" 
					digg="0" 
					reply="1" 
					copy="复制链接" 
					view="查看" 
					deleted="删除" 
					>%E5%BF%98%E6%8E%89%E6%8A%8A%E3%80%82%E3%80%82%E4%BB%80%E4%B9%88%E9%83%BD%E6%B2%A1%E5%8F%91%E7%94%9F%E5%93%A6</item>
<item
					author="01" 
					authorUid="1" 
					clickto="itemId-28" 
					authorHead="../uc.shenei.net/avatar.php@type=real&uid=1&size=small" 
					itemId="28" 
					dateline="2010-01-20" 
					digg="0" 
					reply="0" 
					copy="复制链接" 
					view="查看" 
					deleted="删除" 
					>%E6%98%A5%E5%93%A5%E5%95%8A%EF%BC%8C%E6%98%8E%E5%A4%A9%E8%80%83%E8%AF%95%E8%A6%81%E8%BF%87%E5%95%8A%EF%BC%81%EF%BC%81</item>
<item
					author="ybxstc" 
					authorUid="23" 
					clickto="itemId-27" 
					authorHead="../uc.shenei.net/avatar.php@type=real&uid=23&size=small" 
					itemId="27" 
					dateline="2010-01-18" 
					digg="0" 
					reply="0" 
					copy="复制链接" 
					view="查看" 
					deleted="删除" 
					>%EF%BC%81%EF%BC%81%EF%BC%81%EF%BC%81%EF%BC%81%EF%BC%81%EF%BC%81%EF%BC%81%EF%BC%81%EF%BC%81%EF%BC%81%EF%BC%81%EF%BC%81%EF%BC%81%EF%BC%81%EF%BC%81%EF%BC%81%EF%BC%81%EF%BC%81%EF%BC%81%EF%BC%81%EF%BC%81%EF%BC%81%EF%BC%81%EF%BC%81%EF%BC%81%EF%BC%81%EF%BC%81%EF%BC%81%EF%BC%81%EF%BC%81%EF%BC%81%EF%BC%81%EF%BC%81%EF%BC%81%EF%BC%81%EF%BC%81%EF%BC%81%EF%BC%81%EF%BC%81%EF%BC%81%EF%BC%81%EF%BC%81%EF%BC%81%EF%BC%81%EF%BC%81%EF%BC%81%EF%BC%81%EF%BC%81%EF%BC%81%EF%BC%81%EF%BC%81%EF%BC%81%EF%BC%81%EF%BC%81%EF%BC%81%EF%BC%81%EF%BC%81%EF%BC%81%EF%BC%81%EF%BC%81%EF%BC%81%EF%BC%81</item>
<item
					author="xi77" 
					authorUid="4" 
					clickto="itemId-26" 
					authorHead="../uc.shenei.net/avatar.php@type=real&uid=4&size=small" 
					itemId="26" 
					dateline="2010-01-15" 
					digg="0" 
					reply="0" 
					copy="复制链接" 
					view="查看" 
					deleted="删除" 
					>18%E6%8A%8A%E7%A4%BE%E4%BC%9A%E5%AD%A6%E8%AE%BA%E6%96%87%E4%BA%A4%E4%BA%86%E3%80%82%E3%80%82%E3%80%82%7E%7E%7E%7E%28%26gt%3B_%26lt%3B%29%7E%7E%7E%7E%20%E5%88%9A%E5%86%99%E5%AE%8C%E4%BA%94%E5%8D%83%E5%AD%97%E3%80%82%E8%BF%98%E6%9C%89%E4%B8%89%E5%8D%83%E5%AD%97%EF%BC%81</item>
<item
					author="ybxstc" 
					authorUid="23" 
					clickto="itemId-25" 
					authorHead="../uc.shenei.net/avatar.php@type=real&uid=23&size=small" 
					itemId="25" 
					dateline="2010-01-14" 
					digg="0" 
					reply="0" 
					copy="复制链接" 
					view="查看" 
					deleted="删除" 
					>%21%21%21%21%21%21%21%21%21%21%21%21%21%21%21%21%21%21%21%21%21%21%21%21%21%21%21%21%21%21%21%21%21%21%21%21%21%21%21%21%21%21%21%21%21%21%21%21%21%21%21%21%21%21%21%21</item>
<item
					author="01" 
					authorUid="1" 
					clickto="itemId-24" 
					authorHead="../uc.shenei.net/avatar.php@type=real&uid=1&size=small" 
					itemId="24" 
					dateline="2010-01-13" 
					digg="0" 
					reply="1" 
					copy="复制链接" 
					view="查看" 
					deleted="删除" 
					>%E8%A6%81%E5%8E%BB%E6%9C%BA%E5%9C%BA%E6%8E%A5%E8%8F%9C%E5%A4%B4%E4%BA%86%E5%93%88%E5%BF%83%E6%83%85%E9%82%A3%E4%B8%AA%E6%BF%80%E5%8A%A8%E5%95%8A%EF%BD%9E</item>
<item
					author="ybxstc" 
					authorUid="23" 
					clickto="itemId-23" 
					authorHead="../uc.shenei.net/avatar.php@type=real&uid=23&size=small" 
					itemId="23" 
					dateline="2010-01-13" 
					digg="0" 
					reply="0" 
					copy="复制链接" 
					view="查看" 
					deleted="删除" 
					>%E5%8F%88%E6%9D%A5%E4%BA%86%EF%BC%81%EF%BC%81%E5%A4%AA%E6%97%A0%E8%81%8A%E4%BA%86%EF%BC%81%EF%BC%81%EF%BC%81%EF%BC%81</item>
<item
					author="01" 
					authorUid="1" 
					clickto="itemId-22" 
					authorHead="../uc.shenei.net/avatar.php@type=real&uid=1&size=small" 
					itemId="22" 
					dateline="2010-01-13" 
					digg="0" 
					reply="0" 
					copy="复制链接" 
					view="查看" 
					deleted="删除" 
					>%E5%94%89%E3%80%82%E3%80%82%E6%88%91%E5%B0%B1%E7%AD%89%E7%9D%80%E6%8C%82%E7%A7%91%E5%90%A7%E3%80%82%E3%80%82%E3%80%82</item>
<item
					author="ybxstc" 
					authorUid="23" 
					clickto="itemId-21" 
					authorHead="../uc.shenei.net/avatar.php@type=real&uid=23&size=small" 
					itemId="21" 
					dateline="2010-01-12" 
					digg="0" 
					reply="0" 
					copy="复制链接" 
					view="查看" 
					deleted="删除" 
					>%E5%8F%88%E6%9D%A5%E5%86%99%E4%B8%80%E5%8F%A5%EF%BC%81%E4%B8%8D%E6%8C%82%E7%A7%91%EF%BC%81</item>
<item
					author="%E6%AE%8B%E9%A3%8E%E8%BF%BD%E6%9C%88" 
					authorUid="27" 
					clickto="itemId-20" 
					authorHead="../uc.shenei.net/avatar.php@type=real&uid=27&size=small" 
					itemId="20" 
					dateline="2010-01-08" 
					digg="0" 
					reply="2" 
					copy="复制链接" 
					view="查看" 
					deleted="删除" 
					>%E6%9C%80%E8%BF%91%E7%BD%91%E7%AE%A1%E6%9F%A5%E7%AE%A1%E5%BE%97%E5%BE%88%E4%B8%A5%EF%BC%8C%E5%BE%88%E5%A4%9A%E7%BD%91%E7%AB%99%E9%83%BD%E8%A2%AB%E9%87%8D%E6%96%B0%E5%AE%A1%E6%A0%B8</item>
<item
					author="ybxstc" 
					authorUid="23" 
					clickto="itemId-19" 
					authorHead="../uc.shenei.net/avatar.php@type=real&uid=23&size=small" 
					itemId="19" 
					dateline="2010-01-05" 
					digg="0" 
					reply="1" 
					copy="复制链接" 
					view="查看" 
					deleted="删除" 
					>%E4%B8%8D%E8%A6%81%E6%8C%82%E7%A7%91%E5%95%8A%E5%95%8A%E5%95%8A%E5%95%8A%E5%95%8A%E5%95%8A%E5%95%8A%E5%95%8A%E5%95%8A%E5%95%8A%E5%95%8A</item>
<item
					author="01" 
					authorUid="1" 
					clickto="itemId-18" 
					authorHead="../uc.shenei.net/avatar.php@type=real&uid=1&size=small" 
					itemId="18" 
					dateline="2010-01-03" 
					digg="0" 
					reply="2" 
					copy="复制链接" 
					view="查看" 
					deleted="删除" 
					>%E6%96%B0%E7%9A%84%E4%B8%80%E5%B9%B4%EF%BC%8C%E4%B8%8D%E5%A5%BD%E7%9A%84%E5%BC%80%E5%A7%8B%EF%BC%8C%EF%BC%8C%E6%88%91%E8%A6%81%E5%BC%80%E5%A7%8B%E6%89%93%E9%80%86%E5%A2%83%E7%89%8C%E4%BA%86%E3%80%82%E3%80%82%E3%80%82</item>
<item
					author="fei1019" 
					authorUid="9" 
					clickto="itemId-17" 
					authorHead="../uc.shenei.net/avatar.php@type=real&uid=9&size=small" 
					itemId="17" 
					dateline="2010-01-03" 
					digg="1" 
					reply="1" 
					copy="复制链接" 
					view="查看" 
					deleted="删除" 
					>%E6%96%B0%E5%B9%B4%EF%BC%8C%EF%BC%8C%EF%BC%8C%E6%96%B0%E7%9A%84%E5%BC%80%E5%A7%8B%EF%BC%8C%E4%B8%80%E5%88%87%E9%83%BD%E6%98%AF%E6%96%B0%E7%9A%84%E3%80%82%0D%E6%88%91%E4%B9%9F%E8%A6%81%E7%94%A8%E6%96%B0%E7%9A%84%E5%BF%83%E6%83%85%E5%8E%BB%E9%9D%A2%E5%AF%B9%E6%96%B0%E7%9A%84%E4%B8%80%E5%B9%B4%E3%80%82%E3%80%82%E3%80%82new%20%20starting%2Cnew%20attitution%21</item>
<item
					author="%E6%AE%8B%E9%A3%8E%E8%BF%BD%E6%9C%88" 
					authorUid="27" 
					clickto="itemId-16" 
					authorHead="../uc.shenei.net/avatar.php@type=real&uid=27&size=small" 
					itemId="16" 
					dateline="2010-01-03" 
					digg="0" 
					reply="1" 
					copy="复制链接" 
					view="查看" 
					deleted="删除" 
					>%E6%88%91%E6%9C%89%E7%A7%8D%E6%94%BE%E5%BC%83%E8%87%AA%E5%B7%B1%E7%9A%84%E6%84%9F%E8%A7%89%E4%BA%86</item>
<item
					author="xi77" 
					authorUid="4" 
					clickto="itemId-15" 
					authorHead="../uc.shenei.net/avatar.php@type=real&uid=4&size=small" 
					itemId="15" 
					dateline="2010-01-03" 
					digg="0" 
					reply="1" 
					copy="复制链接" 
					view="查看" 
					deleted="删除" 
					>%E8%80%83%E5%8D%B7%E8%80%83%E3%80%82%E3%80%82%E3%80%82%E3%80%82</item>
<item
					author="Sweet" 
					authorUid="2" 
					clickto="itemId-14" 
					authorHead="../uc.shenei.net/avatar.php@type=real&uid=2&size=small" 
					itemId="14" 
					dateline="2010-01-03" 
					digg="0" 
					reply="1" 
					copy="复制链接" 
					view="查看" 
					deleted="删除" 
					>%E5%B8%8C%E6%9C%9B%E4%BD%A0%E4%BB%AC%E6%B0%B8%E8%BF%9C%E5%BF%AB%E4%B9%90%20...</item>
<item
					author="ybxstc" 
					authorUid="23" 
					clickto="itemId-13" 
					authorHead="../uc.shenei.net/avatar.php@type=real&uid=23&size=small" 
					itemId="13" 
					dateline="2010-01-02" 
					digg="0" 
					reply="1" 
					copy="复制链接" 
					view="查看" 
					deleted="删除" 
					>%E6%98%A8%E5%A4%A9%E6%8C%82%E7%A7%91%E4%BA%86%EF%BC%81%E5%A5%BD%E4%BC%A4%E5%BF%83%EF%BC%81%E4%BB%A5%E5%90%8E%E9%83%BD%E4%B8%8D%E8%A6%81%E6%8C%82%E4%BA%86%EF%BC%81%EF%BC%81%EF%BC%81</item>
<item
					author="01" 
					authorUid="1" 
					clickto="itemId-12" 
					authorHead="../uc.shenei.net/avatar.php@type=real&uid=1&size=small" 
					itemId="12" 
					dateline="2010-01-02" 
					digg="0" 
					reply="2" 
					copy="复制链接" 
					view="查看" 
					deleted="删除" 
					>%E4%BB%8A%E5%A4%A9%E8%A6%81%E5%92%8C%E9%9D%93%E5%A6%B9%E5%8E%BB%E7%9C%8B%E7%94%B5%E5%BD%B1%E5%92%AF%7E%E6%BF%80%E5%8A%A8ing%E2%80%A6</item>
<item
					author="%E6%AE%8B%E9%A3%8E%E8%BF%BD%E6%9C%88" 
					authorUid="27" 
					clickto="itemId-11" 
					authorHead="../uc.shenei.net/avatar.php@type=real&uid=27&size=small" 
					itemId="11" 
					dateline="2010-01-02" 
					digg="0" 
					reply="1" 
					copy="复制链接" 
					view="查看" 
					deleted="删除" 
					>%E4%B8%80%E5%A4%A9%E5%B0%B1%E8%BF%99%E4%B9%88%E8%BF%87%E4%BA%86%7E%7E%E5%B8%8C%E6%9C%9B%E6%96%B0%E5%B9%B4%E9%87%8C%E6%AF%8F%E5%A4%A9%E5%90%83%E5%88%B0%E6%97%A9%E9%A5%AD</item>
<item
					author="01" 
					authorUid="1" 
					clickto="itemId-10" 
					authorHead="../uc.shenei.net/avatar.php@type=real&uid=1&size=small" 
					itemId="10" 
					dateline="2009-12-31" 
					digg="0" 
					reply="0" 
					copy="复制链接" 
					view="查看" 
					deleted="删除" 
					>%E7%8F%8D%E6%83%9C09%E5%B9%B4%E7%9A%84%E6%9C%80%E5%90%8E%E4%B8%80%E5%A4%A9%E5%93%88%7E</item>
<item
					author="xi77" 
					authorUid="4" 
					clickto="itemId-9" 
					authorHead="../uc.shenei.net/avatar.php@type=real&uid=4&size=small" 
					itemId="9" 
					dateline="2009-12-30" 
					digg="0" 
					reply="1" 
					copy="复制链接" 
					view="查看" 
					deleted="删除" 
					>%E5%A4%AA%E9%98%B3%E5%88%AB%E6%87%92%E5%BA%8A%E5%95%8A%E3%80%82%E3%80%82%E5%87%BA%E6%9D%A5%E7%9C%8B%E7%9C%8B%E6%88%91%E5%98%9B</item>
<item
					author="FengLee" 
					authorUid="32" 
					clickto="itemId-8" 
					authorHead="../uc.shenei.net/avatar.php@type=real&uid=32&size=small" 
					itemId="8" 
					dateline="2009-12-30" 
					digg="0" 
					reply="1" 
					copy="复制链接" 
					view="查看" 
					deleted="删除" 
					>%E6%88%91%E5%9C%A8%EF%BC%8C%E9%98%BB%E9%9A%94%E4%B8%8D%E5%9C%A8%E2%80%A6</item>
<item
					author="e5201" 
					authorUid="111" 
					clickto="itemId-7" 
					authorHead="../uc.shenei.net/avatar.php@type=real&uid=111&size=small" 
					itemId="7" 
					dateline="2009-12-30" 
					digg="3" 
					reply="0" 
					copy="复制链接" 
					view="查看" 
					deleted="删除" 
					>%E4%BB%8A%E5%A4%A9%E6%88%91%E4%BB%AC%E5%AD%A6%E6%A0%A1%E5%9C%A3%E8%88%9E%E5%A0%82%E8%80%83%E4%BA%8C%E7%BA%BF%E6%88%91%E6%9D%A5%E7%BB%84%E7%BB%87%E5%93%88%7E%E6%B2%A1%E6%83%B3%E5%88%B0%E6%88%91%E6%9D%83%E5%88%A9%E8%BF%99%E4%B9%88%E5%A4%A7%E5%93%88%EF%BC%81</item>
<item
					author="weibin" 
					authorUid="40" 
					clickto="itemId-6" 
					authorHead="../uc.shenei.net/avatar.php@type=real&uid=40&size=small" 
					itemId="6" 
					dateline="2009-12-29" 
					digg="0" 
					reply="1" 
					copy="复制链接" 
					view="查看" 
					deleted="删除" 
					>%E5%9C%A8%E4%B8%80%E8%B5%B7%EF%BC%8C%E5%BE%88%E7%88%B1%E4%BD%A0</item>
<item
					author="hongling" 
					authorUid="144" 
					clickto="itemId-5" 
					authorHead="../uc.shenei.net/avatar.php@type=real&uid=144&size=small" 
					itemId="5" 
					dateline="2009-12-29" 
					digg="0" 
					reply="2" 
					copy="复制链接" 
					view="查看" 
					deleted="删除" 
					>%EF%BC%8C%EF%BC%8C%E7%94%9F%E6%97%A5%E5%BF%AB%E4%B9%90%EF%BC%8C%EF%BC%8C</item>
<item
					author="e5201" 
					authorUid="111" 
					clickto="itemId-4" 
					authorHead="../uc.shenei.net/avatar.php@type=real&uid=111&size=small" 
					itemId="4" 
					dateline="2009-12-29" 
					digg="3" 
					reply="1" 
					copy="复制链接" 
					view="查看" 
					deleted="删除" 
					>%E6%9C%89%E4%BA%BA%E7%BA%A6%E7%9C%8B%E7%94%B5%E5%BD%B1%E5%93%88%E5%A5%BD%E5%BF%83%E6%83%85%7E</item>
<item
					author="fei1019" 
					authorUid="9" 
					clickto="itemId-3" 
					authorHead="../uc.shenei.net/avatar.php@type=real&uid=9&size=small" 
					itemId="3" 
					dateline="2009-12-28" 
					digg="1" 
					reply="1" 
					copy="复制链接" 
					view="查看" 
					deleted="删除" 
					>%E6%88%91%E8%BA%AB%E8%BE%B9%E6%89%80%E6%9C%89%E7%9A%84%E4%BA%BA%EF%BC%8C%E8%A6%81%E4%B8%80%E7%9B%B4%E5%BF%AB%E4%B9%90%7E%7E</item>
<item
					author="ybxstc" 
					authorUid="23" 
					clickto="itemId-2" 
					authorHead="../uc.shenei.net/avatar.php@type=real&uid=23&size=small" 
					itemId="2" 
					dateline="2009-12-28" 
					digg="1" 
					reply="0" 
					copy="复制链接" 
					view="查看" 
					deleted="删除" 
					>%E6%B0%B8%E8%BF%9C%E4%B8%8D%E6%8C%82%E7%A7%91%EF%BC%81%EF%BC%81%EF%BC%81</item>
<item
					author="01" 
					authorUid="1" 
					clickto="itemId-1" 
					authorHead="../uc.shenei.net/avatar.php@type=real&uid=1&size=small" 
					itemId="1" 
					dateline="2009-12-28" 
					digg="4" 
					reply="0" 
					copy="复制链接" 
					view="查看" 
					deleted="删除" 
					>%E6%88%91%E8%A1%A8%E6%8C%82%E7%A7%91%E5%95%8A%EF%BD%9E%EF%BD%9E%EF%BD%9E</item>
<hotitem
						author="01" 
						authorUid="1" 
						clickto="itemId-1" 
						authorHead="../uc.shenei.net/avatar.php@type=real&uid=1&size=small" 
						itemId="1" 
						dateline="2009-12-28" 
						digg="4" 
						reply="0" 
						copy="复制链接" 
						view="查看" 
						deleted="删除" 
						>%E6%88%91%E8%A1%A8%E6%8C%82%E7%A7%91%E5%95%8A%EF%BD%9E%EF%BD%9E%EF%BD%9E</hotitem>
<hotitem
						author="e5201" 
						authorUid="111" 
						clickto="itemId-4" 
						authorHead="../uc.shenei.net/avatar.php@type=real&uid=111&size=small" 
						itemId="4" 
						dateline="2009-12-29" 
						digg="3" 
						reply="1" 
						copy="复制链接" 
						view="查看" 
						deleted="删除" 
						>%E6%9C%89%E4%BA%BA%E7%BA%A6%E7%9C%8B%E7%94%B5%E5%BD%B1%E5%93%88%E5%A5%BD%E5%BF%83%E6%83%85%7E</hotitem>
<hotitem
						author="e5201" 
						authorUid="111" 
						clickto="itemId-7" 
						authorHead="../uc.shenei.net/avatar.php@type=real&uid=111&size=small" 
						itemId="7" 
						dateline="2009-12-30" 
						digg="3" 
						reply="0" 
						copy="复制链接" 
						view="查看" 
						deleted="删除" 
						>%E4%BB%8A%E5%A4%A9%E6%88%91%E4%BB%AC%E5%AD%A6%E6%A0%A1%E5%9C%A3%E8%88%9E%E5%A0%82%E8%80%83%E4%BA%8C%E7%BA%BF%E6%88%91%E6%9D%A5%E7%BB%84%E7%BB%87%E5%93%88%7E%E6%B2%A1%E6%83%B3%E5%88%B0%E6%88%91%E6%9D%83%E5%88%A9%E8%BF%99%E4%B9%88%E5%A4%A7%E5%93%88%EF%BC%81</hotitem>
<hotitem
						author="Sweet" 
						authorUid="2" 
						clickto="itemId-57" 
						authorHead="../uc.shenei.net/avatar.php@type=real&uid=2&size=small" 
						itemId="57" 
						dateline="2010-04-12" 
						digg="2" 
						reply="0" 
						copy="复制链接" 
						view="查看" 
						deleted="删除" 
						>%E6%88%91%E6%83%B3%E5%9C%A811%E7%82%B9%E5%8D%8A%E4%B9%8B%E5%89%8D%E7%9D%A1%E8%A7%89...</hotitem>
<hotitem
						author="fei1019" 
						authorUid="9" 
						clickto="itemId-17" 
						authorHead="../uc.shenei.net/avatar.php@type=real&uid=9&size=small" 
						itemId="17" 
						dateline="2010-01-03" 
						digg="1" 
						reply="1" 
						copy="复制链接" 
						view="查看" 
						deleted="删除" 
						>%E6%96%B0%E5%B9%B4%EF%BC%8C%EF%BC%8C%EF%BC%8C%E6%96%B0%E7%9A%84%E5%BC%80%E5%A7%8B%EF%BC%8C%E4%B8%80%E5%88%87%E9%83%BD%E6%98%AF%E6%96%B0%E7%9A%84%E3%80%82%0D%E6%88%91%E4%B9%9F%E8%A6%81%E7%94%A8%E6%96%B0%E7%9A%84%E5%BF%83%E6%83%85%E5%8E%BB%E9%9D%A2%E5%AF%B9%E6%96%B0%E7%9A%84%E4%B8%80%E5%B9%B4%E3%80%82%E3%80%82%E3%80%82new%20%20starting%2Cnew%20attitution%21</hotitem>
</items>